nkit/.git/COMMIT_EDITMSG
nkit/.git/config
nkit/.git/description
nkit/.git/HEAD
nkit/.git/hooks/applypatch-msg.sample
nkit/.git/hooks/commit-msg.sample
nkit/.git/hooks/fsmonitor-watchman.sample
nkit/.git/hooks/post-update.sample
nkit/.git/hooks/pre-applypatch.sample
nkit/.git/hooks/pre-commit.sample
nkit/.git/hooks/pre-merge-commit.sample
nkit/.git/hooks/pre-push.sample
nkit/.git/hooks/pre-rebase.sample
nkit/.git/hooks/pre-receive.sample
nkit/.git/hooks/prepare-commit-msg.sample
nkit/.git/hooks/push-to-checkout.sample
nkit/.git/hooks/sendemail-validate.sample
nkit/.git/hooks/update.sample
nkit/.git/index
nkit/.git/info/exclude
nkit/.git/logs/HEAD
nkit/.git/logs/refs/heads/main
nkit/.git/logs/refs/heads/master
nkit/.git/logs/refs/remotes/origin/main
nkit/.git/objects/02/41ecd15e4bb8f87f5d02378ee61c40ce9b118f
nkit/.git/objects/05/62ea1a3412ae2483d0638c96957542f54ab544
nkit/.git/objects/0c/5cf8fcd50817da470152b9ed543beef6f9c81d
nkit/.git/objects/0f/a166c7e354af893978f6491d730ebeede82aab
nkit/.git/objects/16/6b37b937bf90d833e288af692abb309af02fe3
nkit/.git/objects/16/9ee9200ba927ef0feb76e227b7f31d6efbc876
nkit/.git/objects/1c/2f11828ea810848c8e42ce3a7931ec4aba1391
nkit/.git/objects/1c/e58c252d36fc247c126038576b5a7bad307315
nkit/.git/objects/1e/7e777fc309f128b5403e66667205b0a7197155
nkit/.git/objects/27/f8d2dd9ad43ccd391fc09ae289dad5cc1f2f62
nkit/.git/objects/34/bd6a100e57a15bff454e8aa0ae56b8a13bc6ad
nkit/.git/objects/35/a437ce9b31a81e1f869a8f7ab753539c0fffa2
nkit/.git/objects/3a/49e1e44785471824aa2782ba7033283acef193
nkit/.git/objects/44/048941ab14173b2c2ac75234f1dd7d0b7d5066
nkit/.git/objects/45/1eb77fa69f0014ccb44408aae8a80e65acc0f5
nkit/.git/objects/49/642bd732bdcf625db2cf75a5a693c89cde1a81
nkit/.git/objects/49/89099c4e2ca6d0ada9fa333217c369f1511042
nkit/.git/objects/5a/56a86d76476633a07f7bf1e1fcabd298d9d136
nkit/.git/objects/5c/7ff220808b851bf0b9fdcbdf3e8970d5757e6c
nkit/.git/objects/5d/df111af4aaf8a58b12428b53d0e99dfcc79a0b
nkit_agents-0.4.0.dist-info/entry_points.txt
nkit_agents-0.4.0.dist-info/METADATA
nkit_agents-0.4.0.dist-info/WHEEL
nkit_agents-0.4.0.dist-info/RECORD
