Metadata-Version: 2.4
Name: Nkit-Agents
Version: 0.4.0
Summary: A lightweight library for building ReACT-based AI agents that use tools to solve tasks.
Author: NavuluriBalaji
Author-email: navuluribalaji03@gmail.com
Requires-Python: >=3.8.1,<4.0
Classifier: Programming Language :: Python :: 3
Classifier: Programming Language :: Python :: 3.9
Classifier: Programming Language :: Python :: 3.10
Classifier: Programming Language :: Python :: 3.11
Classifier: Programming Language :: Python :: 3.12
Classifier: Programming Language :: Python :: 3.13
Classifier: Programming Language :: Python :: 3.14
Requires-Dist: aiohttp (>=3.9.0,<4.0.0)
Requires-Dist: requests (>=2.31.0,<3.0.0)
